blockprint/__init__.py
blockprint/__main__.py
blockprint/model/__init__.py
blockprint/model/model.py
blockprint-0.0.0.dist-info/METADATA
blockprint-0.0.0.dist-info/WHEEL
blockprint-0.0.0.dist-info/top_level.txt
blockprint-0.0.0.dist-info/zip-safe
blockprint-0.0.0.dist-info/RECORD
